pdfparser/__init__.py
pdfparser/pdfparser.py
pdfparser-1.0.0.dist-info/DESCRIPTION.rst
pdfparser-1.0.0.dist-info/METADATA
pdfparser-1.0.0.dist-info/RECORD
pdfparser-1.0.0.dist-info/WHEEL
pdfparser-1.0.0.dist-info/metadata.json
pdfparser-1.0.0.dist-info/top_level.txt
