Metadata-Version: 2.0
Name: pdfparser
Version: 1.0.0
Summary: pdf parsing tools
Home-page: UNKNOWN
Author: Bryant Moscon
Author-email: bmoscon@gmail.com
License: UNKNOWN
Platform: UNKNOWN
Requires-Dist: pdftotext
